agentia_app/__init__.py
agentia_app/api.py
agentia_app/main.py
agentia_app/plugins/__init__.py
agentia_app/plugins/gmail.py
agentia_app/plugins/mstodo.py
agentia_app/utils/__init__.py
agentia_app/utils/chat.py
agentia_app/utils/oauth.py
agentia_app/web/1_chat.py
agentia_app/web/2_dashboard.py
agentia_app/web/app.py
agentia_app-0.0.2.dist-info/METADATA
agentia_app-0.0.2.dist-info/WHEEL
agentia_app-0.0.2.dist-info/entry_points.txt
agentia_app-0.0.2.dist-info/RECORD
